setup.py
memeyankm_distributions/Binomialdistribution.py
memeyankm_distributions/Gaussiandistribution.py
memeyankm_distributions/Generaldistribution.py
memeyankm_distributions/__init__.py
memeyankm_distributions.egg-info/PKG-INFO
memeyankm_distributions.egg-info/SOURCES.txt
memeyankm_distributions.egg-info/dependency_links.txt
memeyankm_distributions.egg-info/not-zip-safe
memeyankm_distributions.egg-info/top_level.txt