Metadata-Version: 1.0
Name: memeyankm-distributions
Version: 0.69
Summary: Gaussian and Binomial distributions
Home-page: UNKNOWN
Author: memeyankm
Author-email: UNKNOWN
License: UNKNOWN
Platform: UNKNOWN
